pyawscli/__init__.py
pyawscli/__main__.py
pyawscli/colored.py
pyawscli/ec2.py
pyawscli/iam.py
pyawscli/progressbar.py
pyawscli/s3.py
pyawscli-0.1.7.dist-info/LICENSE
pyawscli-0.1.7.dist-info/METADATA
pyawscli-0.1.7.dist-info/WHEEL
pyawscli-0.1.7.dist-info/top_level.txt
pyawscli-0.1.7.dist-info/RECORD
