Metadata-Version: 2.1
Name: pyawscli
Version: 0.1.7
Summary: A CLI package in python to interact with AWS services
Home-page: https://github.com/darshan-raul/Python-Package-for-CLI
Author: Darshan Raul
Author-email: cloudforteskills@gmail.com
License: MIT
Platform: UNKNOWN
Requires-Dist: awscli (<2.0.0,>=1.16.10)
Requires-Dist: boto3 (<2.0.0,>=1.9.0)
Requires-Dist: pyfiglet (<0.8,>=0.7)
Requires-Dist: PyInquirer (>=1.0.3)
Requires-Dist: progress (>=1.5)
Requires-Dist: termcolor (>=1.1.0)
